aiocdp/__init__.py
aiocdp/exceptions.py
aiocdp/ioc.py
aiocdp/logging.py
aiocdp/setup.py
aiocdp/utils.py
aiocdp/core/__init__.py
aiocdp/core/implementations/__init__.py
aiocdp/core/implementations/chrome.py
aiocdp/core/implementations/connection.py
aiocdp/core/implementations/session.py
aiocdp/core/implementations/stream.py
aiocdp/core/implementations/target.py
aiocdp/core/interfaces/__init__.py
aiocdp/core/interfaces/chrome.py
aiocdp/core/interfaces/connection.py
aiocdp/core/interfaces/session.py
aiocdp/core/interfaces/stream.py
aiocdp/core/interfaces/target.py
aiocdp-1.1.8.dist-info/METADATA
aiocdp-1.1.8.dist-info/WHEEL
aiocdp-1.1.8.dist-info/top_level.txt
aiocdp-1.1.8.dist-info/RECORD
