Metadata-Version: 2.1
Name: aiocdp
Version: 1.1.8
Summary: Asynchronous python module for programatic access to Chrome DevTools Protocol.
Author-email: Amir Sharapov <amirsharapov.personal@gmail.com>
Project-URL: Homepage, https://github.com/amirsharapov/aiocdp
Keywords: cdp,chrome devtools protocol,chrome,devtools,browser,automation
Classifier: Programming Language :: Python
Classifier: Programming Language :: Python :: 3
Requires-Python: >=3.9
Requires-Dist: websockets
Requires-Dist: requests
